bootstrap_env/__init__.py
bootstrap_env/boot_bootstrap_env.py
bootstrap_env/bootstrap_env_admin.py
bootstrap_env/version.py
bootstrap_env/admin_shell/__init__.py
bootstrap_env/admin_shell/developer_shell.py
bootstrap_env/admin_shell/normal_shell.py
bootstrap_env/admin_shell/path_helper.py
bootstrap_env/requirements/README.txt
bootstrap_env/requirements/basic_requirements.txt
bootstrap_env/requirements/developer_installation.txt
bootstrap_env/requirements/normal_installation.txt
bootstrap_env/requirements/test_requirements.txt
bootstrap_env/tests/__init__.py
bootstrap_env/tests/base.py
bootstrap_env/tests/manual_bootstrap_dev_test_linux.sh
bootstrap_env/tests/manual_bootstrap_normal_test_linux.sh
bootstrap_env/tests/test_admin.py
bootstrap_env/tests/test_boot.py
bootstrap_env/tests/test_import_utils.py
bootstrap_env/tests/test_test_utils.py
bootstrap_env/tests/utils.py
bootstrap_env/utils/__init__.py
bootstrap_env/utils/cookiecutter_utils.py
bootstrap_env/utils/import_utils.py
bootstrap_env-1.0.2.data/scripts/boot_bootstrap_env.py
bootstrap_env-1.0.2.data/scripts/bootstrap_env_admin.py
bootstrap_env-1.0.2.dist-info/LICENSE
bootstrap_env-1.0.2.dist-info/METADATA
bootstrap_env-1.0.2.dist-info/WHEEL
bootstrap_env-1.0.2.dist-info/top_level.txt
bootstrap_env-1.0.2.dist-info/RECORD
