Metadata-Version: 1.2
Name: bootstrap-env
Version: 1.0.2
Summary: Create a complete self contained virtualenv bootstrap file
Home-page: https://github.com/jedie/bootstrap_env
Author: []
Author-email: bootstrap_env@jensdiemer.de
Maintainer: Jens Diemer
Maintainer-email: bootstrap_env@jensdiemer.de
License: UNKNOWN
Platform: UNKNOWN
Classifier: Development Status :: 2 - Pre-Alpha
Classifier: Intended Audience :: Developers
Classifier: License :: OSI Approved :: GNU General Public License v3 or later (GPLv3+)
Classifier: Operating System :: OS Independent
Classifier: Programming Language :: Python :: 3.5
Classifier: Programming Language :: Python :: 3.6
Classifier: Programming Language :: Python :: 3.7
Classifier: Programming Language :: Python :: 3 :: Only
Classifier: Programming Language :: Python :: Implementation :: CPython
Classifier: Programming Language :: Python :: Implementation :: PyPy
Classifier: Topic :: Software Development
Classifier: Topic :: Software Development :: Build Tools
Classifier: Topic :: Software Development :: Code Generators
Classifier: Topic :: Software Development :: Libraries :: Python Modules
Provides: bootstrap_env
Requires-Python: >=3.5
